mcp_sse_fetch_weather/__init__.py
mcp_sse_fetch_weather/__main__.py
mcp_sse_fetch_weather/server.py
dcx_mcp_sse-0.1.0.dist-info/METADATA
dcx_mcp_sse-0.1.0.dist-info/WHEEL
dcx_mcp_sse-0.1.0.dist-info/top_level.txt
dcx_mcp_sse-0.1.0.dist-info/RECORD
